pandas/configfile.py
pandas_config-0.2.2.dist-info/METADATA
pandas_config-0.2.2.dist-info/WHEEL
pandas_config-0.2.2.dist-info/top_level.txt
pandas_config-0.2.2.dist-info/RECORD
