Metadata-Version: 2.4
Name: pandas-config
Version: 0.2.2
Summary: Configure pandas options simply from an INI file.
Author-email: Steve Kossouho <1023091+artscoop@users.noreply.github.com>
Project-URL: homepage, https://github.com/artscoop/pandas-config
Requires-Python: >=3.11
Requires-Dist: black>=25.1.0
Requires-Dist: pandas>=2.0.0
